{
  "sections": {
    "tfw_hero": {
      "type": "tfw-home-hero",
      "settings": {
        "heading": "<p>Additive free.<br\/>Gluten free.<br\/>Dairy Free.<br\/>Vegan friendly.<\/p>",
        "banner_text": "Jams, Chutneys & Relishes Crafted in the Hawkesbury from fresh seasonal ingredients.",
        "button_text": "Explore range",
        "button_link": "shopify:\/\/collections\/all",
        "banner_image": "shopify:\/\/shop_images\/tfw-hero-banner.png"
      }
    },
    "popular_products": {
      "type": "tfw-popular-products",
      "settings": {
        "heading": "Popular Products",
        "button_text": "View all products",
        "button_link": "shopify:\/\/collections\/all",
        "product_list": [
          "apricot-jam",
          "beetroot-relish",
          "hot-mango-chutney",
          "rhubarb-strawberry-jam"
        ],
        "products_per_page": 16,
        "columns_desktop": 4,
        "image_ratio": "adapt",
        "image_shape": "default",
        "show_secondary_image": false,
        "show_vendor": false,
        "show_rating": false,
        "enable_quick_add": false,
        "enable_filtering": true,
        "filter_type": "horizontal",
        "enable_sorting": true,
        "columns_mobile": "2",
        "padding_top": 36,
        "padding_bottom": 36
      }
    },
    "tfw_cta": {
      "type": "tfw-cta",
      "settings": {
        "image": "shopify:\/\/shop_images\/tfw-our-story.jpg",
        "heading": "Lovingly crafted in the Hawkesbury, New South Wales.",
        "button_text": "Our story",
        "button_link": "shopify:\/\/pages\/about"
      }
    },
    "market": {
      "type": "tfw-market-stall",
      "settings": {
      }
    }
  },
  "order": [
    "tfw_hero",
    "popular_products",
    "tfw_cta",
    "market"
  ]
}
